zmy_mcp_server/__init__.py
zmy_mcp_server/server.py
zmy_mcp_server-0.1.2.dist-info/METADATA
zmy_mcp_server-0.1.2.dist-info/WHEEL
zmy_mcp_server-0.1.2.dist-info/entry_points.txt
zmy_mcp_server-0.1.2.dist-info/top_level.txt
zmy_mcp_server-0.1.2.dist-info/RECORD
