Metadata-Version: 2.4
Name: zmy-mcp-server
Version: 0.1.2
Summary: Add your description here
Requires-Python: >=3.12
Requires-Dist: fastmcp>=2.13.0.2
